setup.py
pynameday/__init__.py
pynameday/austria.py
pynameday/core.py
pynameday/czechrepublic.py
pynameday/slovakia.py
pynameday.egg-info/PKG-INFO
pynameday.egg-info/SOURCES.txt
pynameday.egg-info/dependency_links.txt
pynameday.egg-info/top_level.txt