Metadata-Version: 1.0
Name: pynameday
Version: 0.0.3
Summary: Namedays in different countries
Home-page: https://github.com/Adman/pynameday
Author: Adrian Matejov
Author-email: a.matejov@centrum.sk
License: The MIT License (MIT)
Keywords: nameday,calendar,names
Platform: UNKNOWN
